subvenv/__init__.py
subvenv/core.py
subvenv/version.py
subvenv-1.2.0.dist-info/DESCRIPTION.rst
subvenv-1.2.0.dist-info/LICENSE.txt
subvenv-1.2.0.dist-info/METADATA
subvenv-1.2.0.dist-info/RECORD
subvenv-1.2.0.dist-info/WHEEL
subvenv-1.2.0.dist-info/entry_points.txt
subvenv-1.2.0.dist-info/metadata.json
subvenv-1.2.0.dist-info/top_level.txt
