Metadata-Version: 2.0
Name: subvenv
Version: 1.2.0
Summary: A tool for creating virtualenv-friendly Sublime Text project files
Home-page: http://github.com/Railslide/subvenv
Author: Giulia Vergottini
Author-email: hello@railslide.io
License: MIT
Platform: UNKNOWN
Classifier: Development Status :: 5 - Production/Stable
Classifier: Environment :: Console
Classifier: Intended Audience :: Developers
Classifier: License :: OSI Approved :: MIT License
Classifier: Natural Language :: English
Classifier: Programming Language :: Python
Classifier: Programming Language :: Python :: 2
Classifier: Programming Language :: Python :: 2.7
Classifier: Programming Language :: Python :: 3
Classifier: Programming Language :: Python :: 3.4
Classifier: Programming Language :: Python :: 3.5
Classifier: Programming Language :: Python :: 3.6
